directive/__init__.py
directive/bundles.py
directive/cli.py
directive/release.py
directive/server.py
directive/data/directive/cursor/rules/directive-core-protocol.mdc
directive/data/directive/reference/agent_context.md
directive/data/directive/reference/agent_operating_procedure.md
directive/data/directive/reference/templates/impact_template.md
directive/data/directive/reference/templates/implementation_summary_template.md
directive/data/directive/reference/templates/spec_template.md
directive/data/directive/reference/templates/tdr_template.md
directive-1.2.0.dist-info/METADATA
directive-1.2.0.dist-info/WHEEL
directive-1.2.0.dist-info/entry_points.txt
directive-1.2.0.dist-info/licenses/LICENSE
directive-1.2.0.dist-info/RECORD
