Metadata-Version: 2.4
Name: directive
Version: 1.2.0
Summary: Directive CLI and MCP server scaffolding for file-driven agent context.
Project-URL: Homepage, https://github.com/adamwdraper/directive
Project-URL: Repository, https://github.com/adamwdraper/directive
Project-URL: Issues, https://github.com/adamwdraper/directive/issues
Author: Adam Draper
License: MIT License
License-File: LICENSE
Keywords: agent,cli,directive,mcp,templates
Classifier: License :: OSI Approved :: MIT License
Classifier: Operating System :: OS Independent
Classifier: Programming Language :: Python :: 3
Requires-Python: >=3.10
Requires-Dist: mcp>=1.14.1
Provides-Extra: test
Requires-Dist: pytest-cov>=5.0; extra == 'test'
Requires-Dist: pytest>=8.0; extra == 'test'
